ndd_utils4p/__init__.py
ndd_utils4p/commons.py
ndd_utils4p/git.py
ndd_utils4p/jinja.py
ndd_utils4p/json.py
ndd_utils4p/text.py
ndd_utils4p/yaml.py
ndd_utils4p-0.1.0.dist-info/AUTHORS.rst
ndd_utils4p-0.1.0.dist-info/LICENSE.txt
ndd_utils4p-0.1.0.dist-info/METADATA
ndd_utils4p-0.1.0.dist-info/WHEEL
ndd_utils4p-0.1.0.dist-info/top_level.txt
ndd_utils4p-0.1.0.dist-info/RECORD
