Metadata-Version: 2.1
Name: ndd-utils4p
Version: 0.1.0
Summary: Utilities for Python code
Home-page: https://gitlab.com/ddidier/python-ndd-utils4p/
Author: David DIDIER
Author-email: c_inconnu2@yahoo.fr
License: mit
Project-URL: Documentation, https://ddidier.gitlab.io/python-ndd-utils4p/
Platform: any
Classifier: Development Status :: 4 - Beta
Classifier: Programming Language :: Python
Requires-Dist: jinja2 (>=2.8)
Requires-Dist: jmespath (>=0.9)
Requires-Dist: jsonschema (>=3.0)
Requires-Dist: pyyaml (>=3.13)
Provides-Extra: distributing
Requires-Dist: twine (==3.1.1) ; extra == 'distributing'
Requires-Dist: wheel (==0.34.2) ; extra == 'distributing'
Provides-Extra: documenting
Requires-Dist: sphinx (==2.4.4) ; extra == 'documenting'
Requires-Dist: sphinx-rtd-theme (==0.4.3) ; extra == 'documenting'
Requires-Dist: sphinx-prompt (==1.1.0) ; extra == 'documenting'
Provides-Extra: feature_git
Requires-Dist: gitpython (>=3.0) ; extra == 'feature_git'
Provides-Extra: testing
Requires-Dist: expects (>=0.9.0) ; extra == 'testing'
Requires-Dist: flake8 (==3.7.9) ; extra == 'testing'
Requires-Dist: ndd-test4p (==0.4.4) ; extra == 'testing'
Requires-Dist: pylint (==2.4.4) ; extra == 'testing'
Requires-Dist: pytest (==5.4.1) ; extra == 'testing'
Requires-Dist: pytest-cov (==2.8.1) ; extra == 'testing'
Requires-Dist: pytest-mock (==3.1.0) ; extra == 'testing'
Requires-Dist: tox (==3.14.6) ; extra == 'testing'
